weblate_fedora_messaging/__init__.py
weblate_fedora_messaging/apps.py
weblate_fedora_messaging/models.py
weblate_fedora_messaging/tasks.py
weblate_fedora_messaging/tests.py
weblate_fedora_messaging-0.12.dist-info/licenses/LICENSE
weblate_fedora_messaging-0.12.dist-info/METADATA
weblate_fedora_messaging-0.12.dist-info/WHEEL
weblate_fedora_messaging-0.12.dist-info/top_level.txt
weblate_fedora_messaging-0.12.dist-info/RECORD
