Metadata-Version: 2.4
Name: weblate_fedora_messaging
Version: 0.12
Summary: Weblate Fedora Messaging integration
Author-email: Michal Čihař <michal@weblate.org>
License-Expression: GPL-3.0-or-later
Project-URL: Documentation, https://docs.weblate.org/
Project-URL: Download, https://github.com/WeblateOrg/fedora_mesaging
Project-URL: Funding, https://weblate.org/donate/
Project-URL: Homepage, https://weblate.org/
Project-URL: Issue Tracker, https://github.com/WeblateOrg/fedora_messaging/issues
Project-URL: Source Code, https://github.com/WeblateOrg/fedora_messaging
Project-URL: Twitter, https://twitter.com/WeblateOrg
Keywords: gettext,git,i18n,l10n,mercurial,translate
Platform: any
Classifier: Development Status :: 5 - Production/Stable
Classifier: Environment :: Web Environment
Classifier: Framework :: Django
Classifier: Intended Audience :: Developers
Classifier: Intended Audience :: System Administrators
Classifier: Operating System :: OS Independent
Classifier: Programming Language :: Python :: 3 :: Only
Classifier: Programming Language :: Python :: 3
Classifier: Programming Language :: Python :: 3.11
Classifier: Programming Language :: Python :: 3.12
Classifier: Programming Language :: Python :: 3.13
Classifier: Programming Language :: Python
Classifier: Topic :: Internet :: WWW/HTTP :: Dynamic Content
Classifier: Topic :: Internet :: WWW/HTTP
Classifier: Topic :: Software Development :: Internationalization
Classifier: Topic :: Software Development :: Localization
Requires-Python: >=3.11
License-File: LICENSE
Requires-Dist: cryptography>=42.0.2
Requires-Dist: django-appconf<1.2,>=1.0.0
Requires-Dist: Django<5.3,>=5.0
Requires-Dist: fedora-messaging==3.8.0
Requires-Dist: twisted>=23.8.0
Requires-Dist: Weblate>=5.11
Requires-Dist: weblate_schemas>=2025.1
Provides-Extra: lint
Requires-Dist: pre-commit==4.3.0; extra == "lint"
Provides-Extra: test
Requires-Dist: coverage==7.10.4; extra == "test"
Dynamic: license-file
